django_tasks_local-2.0.dist-info/METADATA
django_tasks_local-2.0.dist-info/WHEEL
django_tasks_local-2.0.dist-info/entry_points.txt
django_tasks_local-2.0.dist-info/licenses/LICENSE
django_tasks_local/__init__.py
django_tasks_local/backend.py
django_tasks_local/state.py
django_tasks_local-2.0.dist-info/RECORD
