Metadata-Version: 2.1
Name: django-tasks-local
Version: 2.0
Summary: Zero-infrastructure task backends for Django 6 (thread pool and process pool)
Author-Email: Chris Beaven <smileychris@gmail.com>
License: MIT
Classifier: Development Status :: 4 - Beta
Classifier: Framework :: Django
Classifier: Framework :: Django :: 6.0
Classifier: Intended Audience :: Developers
Classifier: License :: OSI Approved :: MIT License
Classifier: Operating System :: OS Independent
Classifier: Programming Language :: Python :: 3
Classifier: Programming Language :: Python :: 3.12
Classifier: Programming Language :: Python :: 3.13
Project-URL: Homepage, https://github.com/lincolnloop/django-tasks-local
Project-URL: Documentation, https://lincolnloop.github.io/django-tasks-local/
Requires-Python: >=3.12
Requires-Dist: django>=6.0
